{
    "employees": [
        {
            "employeeID": 1,
            "name": "Josh",
            "salary": 50000,
            "departmentName": "QA"
        },
        {
            "employeeID": 2,
            "name": "Omar",
            "salary": 30000,
            "departmentName": "Analyst"
        },
        {
            "employeeID": 3,
            "name": "Keren",
            "salary": 60000,
            "departmentName": "QA"
        },
        {
            "employeeID": 4,
            "name": "Jane",
            "salary": 70000,
            "departmentName": "Analyst"
        },
        {
            "employeeID": 5,
            "name": "Alex",
            "salary": 20000,
            "departmentName": "QA"
        },
        {
            "employeeID": 6,
            "name": "David",
            "salary": 30000,
            "departmentName": "UX"
        },
        {
            "employeeID": 7,
            "name": "Aaron",
            "salary": 50000,
            "departmentName": "UI"
        },
        {
            "employeeID": 8,
            "name": "Katie",
            "salary": 60000,
            "departmentName": "UI"
        },
        {
            "employeeID": 9,
            "name": "Marisol",
            "salary": 70000,
            "departmentName": "UX"
        },
        {
            "employeeID": 10,
            "name": "Hector",
            "salary": 100000,
            "departmentName": "Analyst"
        }
    ]
}
